{"component_grid.md":"BO3_NWRi","component_button.md":"BkfDhJdl","component_fab.md":"n8cKv4Xk","component_divider.md":"C9CNsptc","component_action-sheet.md":"ahv4g1hC","component_checkbox.md":"BKwzjPQD","component_card.md":"CbimaDht","component_navbar.md":"94UbyZUc","component_calendar-view.md":"cmyjd8L-","component_picker.md":"rTu1FnTQ","component_calendar.md":"DqY1a0ip","component_notice-bar.md":"Drjz09Zr","component_backtop.md":"T81YDVvc","component_datetime-picker-view.md":"CQ2VLaF6","component_col-picker.md":"CRd8KG3O","component_number-keyboard.md":"DRasPSJY","component_notify.md":"CDfwgQVl","component_overlay.md":"DYI-8Ure","component_count-down.md":"BQ5fr-zx","component_circle.md":"KBcR2yUp","component_tabs.md":"BR49jrET","component_sort-button.md":"Cywgv6Xb","component_status-tip.md":"BycuFKrB","component_tag.md":"C-aXmgw7","component_toast.md":"BkfPpxhe","component_tooltip.md":"D8JxqGej","component_textarea.md":"y-YxQDeG","component_watermark.md":"Ff2DbF85","component_gap.md":"gocKbTkS","component_transition.md":"Dw4S-gN6","component_icon.md":"GfZwbJIm","component_img-cropper.md":"X4X0z43Y","component_img.md":"BROmuZ84","component_cell.md":"BslDYery","component_input-number.md":"ZBcOsvRP","component_config-provider.md":"DeHreNJx","component_loading.md":"DTcw8bBn","component_collapse.md":"DgDRT12F","component_badge.md":"BacN1gVA","component_loadmore.md":"BPApNs-F","component_progress.md":"CGRfex8K","component_message-box.md":"CYzUstiu","component_radio.md":"DPbf71FF","component_rate.md":"DFcEVG9u","component_resize.md":"UI1sX4d7","component_picker-view.md":"V3UEIuPj","component_popup.md":"DT29wC8i","component_segmented.md":"Dz0mJG2U","component_search.md":"H-vTcLA4","component_skeleton.md":"B7CpZoTd","component_select-picker.md":"JcG_c9R_","component_slider.md":"BNzblgMZ","component_sidebar.md":"C3YaYloO","component_pagination.md":"pASGSN65","component_sticky.md":"Cqxaaj18","component_steps.md":"B_6ES9gN","component_input.md":"y4pFTK93","component_swiper.md":"DdxtpYmV","component_swipe-action.md":"D9HKUSSL","component_index-bar.md":"BZjDzk4M","component_switch.md":"B7Gx7V83","component_upload.md":"o8po9Mz_","component_tabbar.md":"CdL5Z3VM","component_table.md":"BKab9f86","component_drop-menu.md":"DYjJhJ0Q","component_layout.md":"BOhfF2tp","component_curtain.md":"2O_ZETpO","guide_common-problems.md":"D16zWtaQ","component_popover.md":"Ba4dPWHd","component_password-input.md":"fKE1q4y-","guide_introduction.md":"CYYpKxWS","component_form.md":"BEVjl2kU","guide_typography.md":"BnJ3-hIr","reward_donor.md":"DypQNcr-","reward_reward.md":"7baSSJIz","guide_custom-theme.md":"B2xHovBm","guide_quick-use.md":"CFF1VWwA","guide_locale.md":"CmsWz7sb","index.md":"BT8ax0NB","component_datetime-picker.md":"LVz_UdYm","guide_changelog.md":"D9GBdsqG"}
